<live>
	<task-descriptions>
		<task id="6406144" foc_id="39165" execution-time="1" priority="128" core="0" policy-id="0" state="1" arrival-time="470458" start-time="471189" exit-time="0" session="init -> taskloader" thread="85.tumatmul" ram_quota="0" ram_used="1224"/>
		<task id="6492160" foc_id="39185" execution-time="2" priority="128" core="0" policy-id="0" state="1" arrival-time="470468" start-time="471178" exit-time="0" session="init -> taskloader" thread="85.pi" ram_quota="0" ram_used="1224"/>
		<task id="6578176" foc_id="39205" execution-time="1" priority="128" core="0" policy-id="0" state="1" arrival-time="470478" start-time="471211" exit-time="0" session="init -> taskloader" thread="85.linpack" ram_quota="0" ram_used="1224"/>
		<task id="6672384" foc_id="39225" execution-time="7" priority="128" core="0" policy-id="0" state="1" arrival-time="470488" start-time="471010" exit-time="0" session="init -> taskloader" thread="85.hey" ram_quota="0" ram_used="1224"/>
		<task id="6762496" foc_id="39245" execution-time="1" priority="128" core="0" policy-id="0" state="1" arrival-time="470499" start-time="470852" exit-time="0" session="init -> taskloader" thread="85.cond_mod" ram_quota="0" ram_used="1224"/>
		<task id="6864896" foc_id="39265" execution-time="1" priority="128" core="0" policy-id="0" state="1" arrival-time="470509" start-time="470803" exit-time="0" session="init -> taskloader" thread="85.cond_42" ram_quota="0" ram_used="1224"/>
		<task id="0" foc_id="2164409828" execution-time="0" priority="0" core="0" policy-id="0" state="5" arrival-time="9237889903027551" start-time="704913603" exit-time="5383211094001" session="init -> taskloader" thread="84.tumatmul" ram_quota="2112504" ram_used="2112504"/>
		<task id="547" foc_id="2164409536" execution-time="0" priority="2163204108" core="0" policy-id="0" state="5" arrival-time="538967" start-time="704913603" exit-time="9290891123935560" session="init -> taskloader" thread="84.pi" ram_quota="2112504" ram_used="2112504"/>
		<task id="546" foc_id="2164409244" execution-time="0" priority="2163204108" core="0" policy-id="0" state="5" arrival-time="538967" start-time="704913603" exit-time="9290891123935560" session="init -> taskloader" thread="84.linpack" ram_quota="2112504" ram_used="2112504"/>
		<task id="545" foc_id="2164408952" execution-time="0" priority="2163204108" core="0" policy-id="0" state="5" arrival-time="538967" start-time="704913603" exit-time="9290891123935560" session="init -> taskloader" thread="84.hey" ram_quota="2112504" ram_used="2112504"/>
		<task id="544" foc_id="2164408660" execution-time="0" priority="2163204108" core="0" policy-id="0" state="5" arrival-time="538967" start-time="704913603" exit-time="9290891123935560" session="init -> taskloader" thread="84.cond_mod" ram_quota="2112504" ram_used="2112504"/>
		<task id="543" foc_id="2164408368" execution-time="0" priority="2163204108" core="0" policy-id="0" state="5" arrival-time="538967" start-time="704913603" exit-time="9290891123935559" session="init -> taskloader" thread="84.cond_42" ram_quota="2112504" ram_used="2112504"/>
		<task id="542" foc_id="2164395488" execution-time="0" priority="2163204108" core="0" policy-id="0" state="5" arrival-time="538967" start-time="704913603" exit-time="9290891123935546" session="init -> taskloader" thread="83.tumatmul" ram_quota="2112504" ram_used="2112504"/>
		<task id="541" foc_id="2164395196" execution-time="0" priority="2163204108" core="0" policy-id="0" state="5" arrival-time="538967" start-time="704913603" exit-time="9290891123935546" session="init -> taskloader" thread="83.pi" ram_quota="2112504" ram_used="2112504"/>
		<task id="540" foc_id="2164394904" execution-time="0" priority="2163204108" core="0" policy-id="0" state="5" arrival-time="538967" start-time="704913603" exit-time="9290891123935546" session="init -> taskloader" thread="83.linpack" ram_quota="2112504" ram_used="2112504"/>
		<task id="539" foc_id="2164394612" execution-time="0" priority="2163204108" core="0" policy-id="0" state="5" arrival-time="538967" start-time="704913603" exit-time="9290891123935545" session="init -> taskloader" thread="83.hey" ram_quota="2112504" ram_used="2112504"/>
		<task id="538" foc_id="2164394320" execution-time="0" priority="2163204108" core="0" policy-id="0" state="5" arrival-time="538967" start-time="704913603" exit-time="9290891123935545" session="init -> taskloader" thread="83.cond_mod" ram_quota="2112504" ram_used="2112504"/>
		<task id="537" foc_id="2164394028" execution-time="0" priority="2163204108" core="0" policy-id="0" state="5" arrival-time="538967" start-time="704913603" exit-time="9290891123935545" session="init -> taskloader" thread="83.cond_42" ram_quota="2112504" ram_used="2112504"/>
		<task id="536" foc_id="2164393736" execution-time="0" priority="2163204108" core="0" policy-id="0" state="5" arrival-time="538967" start-time="704913603" exit-time="9290891123935545" session="init -> taskloader" thread="82.tumatmul" ram_quota="2112504" ram_used="2112504"/>
		<task id="535" foc_id="2164393444" execution-time="0" priority="2163204108" core="0" policy-id="0" state="5" arrival-time="538967" start-time="704913603" exit-time="9290891123935544" session="init -> taskloader" thread="82.pi" ram_quota="2112504" ram_used="2112504"/>
		<task id="534" foc_id="2164393152" execution-time="0" priority="2163204108" core="0" policy-id="0" state="5" arrival-time="538967" start-time="704913603" exit-time="9290891123935544" session="init -> taskloader" thread="82.linpack" ram_quota="2112504" ram_used="2112504"/>
		<task id="533" foc_id="2164392860" execution-time="0" priority="2163204108" core="0" policy-id="0" state="5" arrival-time="538967" start-time="704913603" exit-time="9290891123935544" session="init -> taskloader" thread="82.hey" ram_quota="2112504" ram_used="2112504"/>
		<task id="532" foc_id="2164392568" execution-time="0" priority="2163204108" core="0" policy-id="0" state="5" arrival-time="538967" start-time="704913603" exit-time="9290891123935543" session="init -> taskloader" thread="82.cond_mod" ram_quota="2112504" ram_used="2112504"/>
		<task id="531" foc_id="2164392276" execution-time="0" priority="2163204108" core="0" policy-id="0" state="5" arrival-time="538967" start-time="704913603" exit-time="9290891123935543" session="init -> taskloader" thread="82.cond_42" ram_quota="2112504" ram_used="2112504"/>
		<task id="530" foc_id="2164391984" execution-time="0" priority="2163204108" core="0" policy-id="0" state="5" arrival-time="538967" start-time="704913603" exit-time="9290891123935543" session="init -> taskloader" thread="81.tumatmul" ram_quota="2112504" ram_used="2112504"/>
		<task id="529" foc_id="2164354528" execution-time="0" priority="2163204108" core="0" policy-id="0" state="5" arrival-time="538967" start-time="704913603" exit-time="9290891123935505" session="init -> taskloader" thread="81.pi" ram_quota="2112504" ram_used="2112504"/>
		<task id="528" foc_id="2164354236" execution-time="0" priority="2163204108" core="0" policy-id="0" state="5" arrival-time="538967" start-time="704913603" exit-time="9290891123935505" session="init -> taskloader" thread="81.linpack" ram_quota="2112504" ram_used="2112504"/>
		<task id="527" foc_id="2164353944" execution-time="0" priority="2163204108" core="0" policy-id="0" state="5" arrival-time="538967" start-time="704913603" exit-time="9290891123935505" session="init -> taskloader" thread="81.hey" ram_quota="2112504" ram_used="2112504"/>
		<task id="526" foc_id="2164353652" execution-time="0" priority="2163204108" core="0" policy-id="0" state="5" arrival-time="538967" start-time="704913603" exit-time="9290891123935505" session="init -> taskloader" thread="81.cond_mod" ram_quota="2112504" ram_used="2112504"/>
		<task id="525" foc_id="2164353360" execution-time="0" priority="2163204108" core="0" policy-id="0" state="5" arrival-time="538967" start-time="704913603" exit-time="9290891123935504" session="init -> taskloader" thread="81.cond_42" ram_quota="2112504" ram_used="2112504"/>
		<task id="524" foc_id="2164353068" execution-time="0" priority="2163204108" core="0" policy-id="0" state="5" arrival-time="538967" start-time="704913603" exit-time="9290891123935504" session="init -> taskloader" thread="80.tumatmul" ram_quota="2112504" ram_used="2112504"/>
		<task id="523" foc_id="2164352776" execution-time="0" priority="2163204108" core="0" policy-id="0" state="5" arrival-time="538967" start-time="704913603" exit-time="9290891123935504" session="init -> taskloader" thread="80.pi" ram_quota="2112504" ram_used="2112504"/>
		<task id="522" foc_id="2164352484" execution-time="0" priority="2163204108" core="0" policy-id="0" state="5" arrival-time="538967" start-time="704913603" exit-time="9290891123935503" session="init -> taskloader" thread="80.linpack" ram_quota="2112504" ram_used="2112504"/>
		<task id="521" foc_id="2164352192" execution-time="0" priority="2163204108" core="0" policy-id="0" state="5" arrival-time="538967" start-time="704913603" exit-time="9290891123935503" session="init -> taskloader" thread="80.hey" ram_quota="2112504" ram_used="2112504"/>
		<task id="520" foc_id="2164351900" execution-time="0" priority="2163204108" core="0" policy-id="0" state="5" arrival-time="538967" start-time="704913603" exit-time="9290891123935503" session="init -> taskloader" thread="80.cond_mod" ram_quota="2112504" ram_used="2112504"/>
		<task id="519" foc_id="2164351608" execution-time="0" priority="2163204108" core="0" policy-id="0" state="5" arrival-time="538967" start-time="704913603" exit-time="9290891123935502" session="init -> taskloader" thread="80.cond_42" ram_quota="2112504" ram_used="2112504"/>
		<task id="518" foc_id="2164351316" execution-time="0" priority="2163204108" core="0" policy-id="0" state="5" arrival-time="538967" start-time="704913603" exit-time="9290891123935502" session="init -> taskloader" thread="79.tumatmul" ram_quota="2112504" ram_used="2112504"/>
		<task id="517" foc_id="2164351024" execution-time="0" priority="2163204108" core="0" policy-id="0" state="5" arrival-time="538967" start-time="704913603" exit-time="9290891123935502" session="init -> taskloader" thread="79.pi" ram_quota="2112504" ram_used="2112504"/>
		<task id="516" foc_id="2164346336" execution-time="0" priority="2163204108" core="0" policy-id="0" state="5" arrival-time="538967" start-time="704913603" exit-time="9290891123935497" session="init -> taskloader" thread="79.linpack" ram_quota="2112504" ram_used="2112504"/>
		<task id="515" foc_id="2164346044" execution-time="0" priority="2163204108" core="0" policy-id="0" state="5" arrival-time="538967" start-time="704913603" exit-time="9290891123935497" session="init -> taskloader" thread="79.hey" ram_quota="2112504" ram_used="2112504"/>
		<task id="514" foc_id="2164345752" execution-time="0" priority="2163204108" core="0" policy-id="0" state="5" arrival-time="538967" start-time="704913603" exit-time="9290891123935497" session="init -> taskloader" thread="79.cond_mod" ram_quota="2112504" ram_used="2112504"/>
		<task id="513" foc_id="2164345460" execution-time="0" priority="2163204108" core="0" policy-id="0" state="5" arrival-time="538967" start-time="704913603" exit-time="9290891123935496" session="init -> taskloader" thread="79.cond_42" ram_quota="2112504" ram_used="2112504"/>
		<task id="512" foc_id="2164345168" execution-time="0" priority="2163204108" core="0" policy-id="0" state="5" arrival-time="538967" start-time="704913603" exit-time="9290891123935496" session="init -> taskloader" thread="78.tumatmul" ram_quota="2112504" ram_used="2112504"/>
		<task id="511" foc_id="2164344876" execution-time="0" priority="2163204108" core="0" policy-id="0" state="5" arrival-time="538967" start-time="704913603" exit-time="9290891123935496" session="init -> taskloader" thread="78.pi" ram_quota="2112504" ram_used="2112504"/>
		<task id="510" foc_id="2164344584" execution-time="0" priority="2163204108" core="0" policy-id="0" state="5" arrival-time="538967" start-time="704913603" exit-time="9290891123935495" session="init -> taskloader" thread="78.linpack" ram_quota="2112504" ram_used="2112504"/>
		<task id="509" foc_id="2164344292" execution-time="0" priority="2163204108" core="0" policy-id="0" state="5" arrival-time="538967" start-time="704913603" exit-time="9290891123935495" session="init -> taskloader" thread="78.hey" ram_quota="2112504" ram_used="2112504"/>
		<task id="508" foc_id="2164344000" execution-time="0" priority="2163204108" core="0" policy-id="0" state="5" arrival-time="538967" start-time="704913603" exit-time="9290891123935495" session="init -> taskloader" thread="78.cond_mod" ram_quota="2112504" ram_used="2112504"/>
		<task id="507" foc_id="2164343708" execution-time="0" priority="2163204108" core="0" policy-id="0" state="5" arrival-time="538967" start-time="704913603" exit-time="9290891123935495" session="init -> taskloader" thread="78.cond_42" ram_quota="2112504" ram_used="2112504"/>
		<task id="506" foc_id="2164343416" execution-time="0" priority="2163204108" core="0" policy-id="0" state="5" arrival-time="538967" start-time="704913603" exit-time="9290891123935494" session="init -> taskloader" thread="77.tumatmul" ram_quota="2112504" ram_used="2112504"/>
		<task id="505" foc_id="2164343124" execution-time="0" priority="2163204108" core="0" policy-id="0" state="5" arrival-time="538967" start-time="704913603" exit-time="9290891123935494" session="init -> taskloader" thread="77.pi" ram_quota="2112504" ram_used="2112504"/>
		<task id="504" foc_id="2164342832" execution-time="0" priority="2163204108" core="0" policy-id="0" state="5" arrival-time="538967" start-time="704913603" exit-time="9290891123935494" session="init -> taskloader" thread="77.linpack" ram_quota="2112504" ram_used="2112504"/>
		<task id="503" foc_id="2164321760" execution-time="0" priority="2163204108" core="0" policy-id="0" state="5" arrival-time="538967" start-time="704913603" exit-time="9290891123935473" session="init -> taskloader" thread="77.hey" ram_quota="2112504" ram_used="2112504"/>
		<task id="502" foc_id="2164321468" execution-time="0" priority="2163204108" core="0" policy-id="0" state="5" arrival-time="538967" start-time="704913603" exit-time="9290891123935472" session="init -> taskloader" thread="77.cond_mod" ram_quota="2112504" ram_used="2112504"/>
		<task id="501" foc_id="2164321176" execution-time="0" priority="2163204108" core="0" policy-id="0" state="5" arrival-time="538967" start-time="704913603" exit-time="9290891123935472" session="init -> taskloader" thread="77.cond_42" ram_quota="2112504" ram_used="2112504"/>
		<task id="500" foc_id="2164320884" execution-time="0" priority="2163204108" core="0" policy-id="0" state="5" arrival-time="538967" start-time="704913603" exit-time="9290891123935472" session="init -> taskloader" thread="76.tumatmul" ram_quota="2112504" ram_used="2112504"/>
		<task id="499" foc_id="2164320592" execution-time="0" priority="2163204108" core="0" policy-id="0" state="5" arrival-time="538967" start-time="704913603" exit-time="9290891123935471" session="init -> taskloader" thread="76.pi" ram_quota="2112504" ram_used="2112504"/>
		<task id="498" foc_id="2164320300" execution-time="0" priority="2163204108" core="0" policy-id="0" state="5" arrival-time="538967" start-time="704913603" exit-time="9290891123935471" session="init -> taskloader" thread="76.linpack" ram_quota="2112504" ram_used="2112504"/>
		<task id="497" foc_id="2164320008" execution-time="0" priority="2163204108" core="0" policy-id="0" state="5" arrival-time="538967" start-time="704913603" exit-time="9290891123935471" session="init -> taskloader" thread="76.hey" ram_quota="2112504" ram_used="2112504"/>
		<task id="496" foc_id="2164319716" execution-time="0" priority="2163204108" core="0" policy-id="0" state="5" arrival-time="538967" start-time="704913603" exit-time="9290891123935471" session="init -> taskloader" thread="76.cond_mod" ram_quota="2112504" ram_used="2112504"/>
		<task id="495" foc_id="2164319424" execution-time="0" priority="2163204108" core="0" policy-id="0" state="5" arrival-time="538967" start-time="704913603" exit-time="9290891123935470" session="init -> taskloader" thread="76.cond_42" ram_quota="2112504" ram_used="2112504"/>
		<task id="494" foc_id="2164319132" execution-time="0" priority="2163204108" core="0" policy-id="0" state="5" arrival-time="538967" start-time="704913603" exit-time="9290891123935470" session="init -> taskloader" thread="75.tumatmul" ram_quota="2112504" ram_used="2112504"/>
		<task id="493" foc_id="2164318840" execution-time="0" priority="2163204108" core="0" policy-id="0" state="5" arrival-time="538967" start-time="704913603" exit-time="9290891123935470" session="init -> taskloader" thread="75.pi" ram_quota="2112504" ram_used="2112504"/>
		<task id="492" foc_id="2164318548" execution-time="0" priority="2163204108" core="0" policy-id="0" state="5" arrival-time="538967" start-time="704913603" exit-time="9290891123935469" session="init -> taskloader" thread="75.linpack" ram_quota="2112504" ram_used="2112504"/>
		<task id="491" foc_id="2164318256" execution-time="0" priority="2163204108" core="0" policy-id="0" state="5" arrival-time="538967" start-time="704913603" exit-time="9290891123935469" session="init -> taskloader" thread="75.hey" ram_quota="2112504" ram_used="2112504"/>
		<task id="490" foc_id="2164297184" execution-time="0" priority="2163204108" core="0" policy-id="0" state="5" arrival-time="538967" start-time="704913603" exit-time="9290891123935448" session="init -> taskloader" thread="75.cond_mod" ram_quota="2112504" ram_used="2112504"/>
		<task id="489" foc_id="2164296892" execution-time="0" priority="2163204108" core="0" policy-id="0" state="5" arrival-time="538967" start-time="704913603" exit-time="9290891123935448" session="init -> taskloader" thread="75.cond_42" ram_quota="2112504" ram_used="2112504"/>
		<task id="488" foc_id="2164296600" execution-time="0" priority="2163204108" core="0" policy-id="0" state="5" arrival-time="538967" start-time="704913603" exit-time="9290891123935447" session="init -> taskloader" thread="74.tumatmul" ram_quota="2112504" ram_used="2112504"/>
		<task id="487" foc_id="2164296308" execution-time="0" priority="2163204108" core="0" policy-id="0" state="5" arrival-time="538967" start-time="704913603" exit-time="9290891123935447" session="init -> taskloader" thread="74.pi" ram_quota="2112504" ram_used="2112504"/>
		<task id="486" foc_id="2164296016" execution-time="0" priority="2163204108" core="0" policy-id="0" state="5" arrival-time="538967" start-time="704913603" exit-time="9290891123935447" session="init -> taskloader" thread="74.linpack" ram_quota="2112504" ram_used="2112504"/>
		<task id="485" foc_id="2164295724" execution-time="0" priority="2163204108" core="0" policy-id="0" state="5" arrival-time="538967" start-time="704913603" exit-time="9290891123935447" session="init -> taskloader" thread="74.hey" ram_quota="2112504" ram_used="2112504"/>
		<task id="484" foc_id="2164295432" execution-time="0" priority="2163204108" core="0" policy-id="0" state="5" arrival-time="538967" start-time="704913603" exit-time="9290891123935446" session="init -> taskloader" thread="74.cond_mod" ram_quota="2112504" ram_used="2112504"/>
		<task id="483" foc_id="2164295140" execution-time="0" priority="2163204108" core="0" policy-id="0" state="5" arrival-time="538967" start-time="704913603" exit-time="9290891123935446" session="init -> taskloader" thread="74.cond_42" ram_quota="2112504" ram_used="2112504"/>
		<task id="482" foc_id="2164294848" execution-time="0" priority="2163204108" core="0" policy-id="0" state="5" arrival-time="538967" start-time="704913603" exit-time="9290891123935446" session="init -> taskloader" thread="73.tumatmul" ram_quota="2112504" ram_used="2112504"/>
		<task id="481" foc_id="2164294556" execution-time="0" priority="2163204108" core="0" policy-id="0" state="5" arrival-time="538967" start-time="704913603" exit-time="9290891123935445" session="init -> taskloader" thread="73.pi" ram_quota="2112504" ram_used="2112504"/>
		<task id="480" foc_id="2164294264" execution-time="0" priority="2163204108" core="0" policy-id="0" state="5" arrival-time="538967" start-time="704913603" exit-time="9290891123935445" session="init -> taskloader" thread="73.linpack" ram_quota="2112504" ram_used="2112504"/>
		<task id="479" foc_id="2164293972" execution-time="0" priority="2163204108" core="0" policy-id="0" state="5" arrival-time="538967" start-time="704913603" exit-time="9290891123935445" session="init -> taskloader" thread="73.hey" ram_quota="2112504" ram_used="2112504"/>
		<task id="478" foc_id="2164293680" execution-time="0" priority="2163204108" core="0" policy-id="0" state="5" arrival-time="538967" start-time="704913603" exit-time="9290891123935445" session="init -> taskloader" thread="73.cond_mod" ram_quota="2112504" ram_used="2112504"/>
		<task id="477" foc_id="2164272608" execution-time="0" priority="2163204108" core="0" policy-id="0" state="5" arrival-time="538967" start-time="704913603" exit-time="9290891123935423" session="init -> taskloader" thread="73.cond_42" ram_quota="2112504" ram_used="2112504"/>
		<task id="476" foc_id="2164272316" execution-time="0" priority="2163204108" core="0" policy-id="0" state="5" arrival-time="538967" start-time="704913603" exit-time="9290891123935423" session="init -> taskloader" thread="72.tumatmul" ram_quota="2112504" ram_used="2112504"/>
		<task id="475" foc_id="2164272024" execution-time="0" priority="2163204108" core="0" policy-id="0" state="5" arrival-time="538967" start-time="704913603" exit-time="9290891123935423" session="init -> taskloader" thread="72.pi" ram_quota="2112504" ram_used="2112504"/>
		<task id="474" foc_id="2164271732" execution-time="0" priority="2163204108" core="0" policy-id="0" state="5" arrival-time="538967" start-time="704913603" exit-time="9290891123935423" session="init -> taskloader" thread="72.linpack" ram_quota="2112504" ram_used="2112504"/>
		<task id="473" foc_id="2164271440" execution-time="0" priority="2163204108" core="0" policy-id="0" state="5" arrival-time="538967" start-time="704913603" exit-time="9290891123935422" session="init -> taskloader" thread="72.hey" ram_quota="2112504" ram_used="2112504"/>
		<task id="472" foc_id="2164271148" execution-time="0" priority="2163204108" core="0" policy-id="0" state="5" arrival-time="538967" start-time="704913603" exit-time="9290891123935422" session="init -> taskloader" thread="72.cond_mod" ram_quota="2112504" ram_used="2112504"/>
		<task id="471" foc_id="2164270856" execution-time="0" priority="2163204108" core="0" policy-id="0" state="5" arrival-time="538967" start-time="704913603" exit-time="9290891123935422" session="init -> taskloader" thread="72.cond_42" ram_quota="2112504" ram_used="2112504"/>
		<task id="470" foc_id="2164270564" execution-time="0" priority="2163204108" core="0" policy-id="0" state="5" arrival-time="538967" start-time="704913603" exit-time="9290891123935421" session="init -> taskloader" thread="71.tumatmul" ram_quota="2112504" ram_used="2112504"/>
		<task id="469" foc_id="2164270272" execution-time="0" priority="2163204108" core="0" policy-id="0" state="5" arrival-time="538967" start-time="704913603" exit-time="9290891123935421" session="init -> taskloader" thread="71.pi" ram_quota="2112504" ram_used="2112504"/>
		<task id="468" foc_id="2164269980" execution-time="0" priority="2163204108" core="0" policy-id="0" state="5" arrival-time="538967" start-time="704913603" exit-time="9290891123935421" session="init -> taskloader" thread="71.linpack" ram_quota="2112504" ram_used="2112504"/>
		<task id="467" foc_id="2164269688" execution-time="0" priority="2163204108" core="0" policy-id="0" state="5" arrival-time="538967" start-time="704913603" exit-time="9290891123935421" session="init -> taskloader" thread="71.hey" ram_quota="2112504" ram_used="2112504"/>
		<task id="466" foc_id="2164269396" execution-time="0" priority="2163204108" core="0" policy-id="0" state="5" arrival-time="538967" start-time="704913603" exit-time="9290891123935420" session="init -> taskloader" thread="71.cond_mod" ram_quota="2112504" ram_used="2112504"/>
		<task id="465" foc_id="2164269104" execution-time="0" priority="2163204108" core="0" policy-id="0" state="5" arrival-time="538967" start-time="704913603" exit-time="9290891123935420" session="init -> taskloader" thread="71.cond_42" ram_quota="2112504" ram_used="2112504"/>
		<task id="464" foc_id="2164370912" execution-time="0" priority="2163204108" core="0" policy-id="0" state="5" arrival-time="538967" start-time="704913603" exit-time="9290891123935522" session="init -> taskloader" thread="70.tumatmul" ram_quota="2112504" ram_used="2112504"/>
		<task id="463" foc_id="2164370620" execution-time="0" priority="2163204108" core="0" policy-id="0" state="5" arrival-time="538967" start-time="704913603" exit-time="9290891123935521" session="init -> taskloader" thread="70.pi" ram_quota="2112504" ram_used="2112504"/>
		<task id="462" foc_id="2164370328" execution-time="0" priority="2163204108" core="0" policy-id="0" state="5" arrival-time="538967" start-time="704913603" exit-time="9290891123935521" session="init -> taskloader" thread="70.linpack" ram_quota="2112504" ram_used="2112504"/>
		<task id="461" foc_id="2164370036" execution-time="0" priority="2163204108" core="0" policy-id="0" state="5" arrival-time="538967" start-time="704913603" exit-time="9290891123935521" session="init -> taskloader" thread="70.hey" ram_quota="2112504" ram_used="2112504"/>
		<task id="460" foc_id="2164369744" execution-time="0" priority="2163204108" core="0" policy-id="0" state="5" arrival-time="538967" start-time="704913603" exit-time="9290891123935521" session="init -> taskloader" thread="70.cond_mod" ram_quota="2112504" ram_used="2112504"/>
		<task id="459" foc_id="2164369452" execution-time="0" priority="2163204108" core="0" policy-id="0" state="5" arrival-time="538967" start-time="704913603" exit-time="9290891123935520" session="init -> taskloader" thread="70.cond_42" ram_quota="2112504" ram_used="2112504"/>
		<task id="458" foc_id="2164369160" execution-time="0" priority="2163204108" core="0" policy-id="0" state="5" arrival-time="538967" start-time="704913603" exit-time="9290891123935520" session="init -> taskloader" thread="69.tumatmul" ram_quota="2112504" ram_used="2112504"/>
		<task id="457" foc_id="2164368868" execution-time="0" priority="2163204108" core="0" policy-id="0" state="5" arrival-time="538967" start-time="704913603" exit-time="9290891123935520" session="init -> taskloader" thread="69.pi" ram_quota="2112504" ram_used="2112504"/>
		<task id="456" foc_id="2164368576" execution-time="0" priority="2163204108" core="0" policy-id="0" state="5" arrival-time="538967" start-time="704913603" exit-time="9290891123935519" session="init -> taskloader" thread="69.linpack" ram_quota="2112504" ram_used="2112504"/>
		<task id="455" foc_id="2164368284" execution-time="0" priority="2163204108" core="0" policy-id="0" state="5" arrival-time="538967" start-time="704913603" exit-time="9290891123935519" session="init -> taskloader" thread="69.hey" ram_quota="2112504" ram_used="2112504"/>
		<task id="0" foc_id="0" execution-time="0" priority="0" core="0" policy-id="0" state="0" arrival-time="0" start-time="0" exit-time="0" session="" thread="" ram_quota="0" ram_used="0"/>
		<task id="0" foc_id="0" execution-time="0" priority="0" core="0" policy-id="0" state="0" arrival-time="0" start-time="0" exit-time="0" session="" thread="" ram_quota="0" ram_used="0"/>
		<task id="0" foc_id="464616000" execution-time="464556" priority="38363" core="464676000" policy-id="38343" state="0" arrival-time="39" start-time="465786" exit-time="465844" session="" thread="" ram_quota="0" ram_used="37"/>
		<task id="0" foc_id="39327" execution-time="39" priority="471835000" core="39357" policy-id="471476000" state="0" arrival-time="0" start-time="0" exit-time="0" session="" thread="" ram_quota="0" ram_used="461791"/>
		<task id="0" foc_id="0" execution-time="0" priority="0" core="0" policy-id="0" state="0" arrival-time="0" start-time="0" exit-time="0" session="" thread="" ram_quota="0" ram_used="0"/>
		<task id="0" foc_id="0" execution-time="0" priority="0" core="0" policy-id="0" state="0" arrival-time="0" start-time="0" exit-time="0" session="" thread="" ram_quota="0" ram_used="0"/>
		<task id="0" foc_id="0" execution-time="0" priority="0" core="0" policy-id="0" state="0" arrival-time="0" start-time="0" exit-time="0" session="" thread="" ram_quota="0" ram_used="0"/>
		<task id="0" foc_id="0" execution-time="0" priority="0" core="0" policy-id="0" state="0" arrival-time="0" start-time="0" exit-time="0" session="" thread="" ram_quota="0" ram_used="0"/>
		<task id="0" foc_id="0" execution-time="0" priority="0" core="0" policy-id="0" state="0" arrival-time="0" start-time="0" exit-time="0" session="" thread="" ram_quota="0" ram_used="0"/>
		<task id="0" foc_id="0" execution-time="0" priority="0" core="0" policy-id="0" state="0" arrival-time="0" start-time="0" exit-time="0" session="" thread="" ram_quota="0" ram_used="0"/>
		<task id="0" foc_id="0" execution-time="0" priority="0" core="0" policy-id="0" state="0" arrival-time="0" start-time="0" exit-time="0" session="" thread="" ram_quota="0" ram_used="0"/>
		<task id="0" foc_id="0" execution-time="0" priority="0" core="0" policy-id="0" state="0" arrival-time="0" start-time="0" exit-time="0" session="" thread="" ram_quota="0" ram_used="0"/>
		<task id="0" foc_id="0" execution-time="0" priority="0" core="0" policy-id="0" state="0" arrival-time="0" start-time="0" exit-time="0" session="" thread="" ram_quota="0" ram_used="0"/>
		<task id="0" foc_id="0" execution-time="0" priority="0" core="0" policy-id="0" state="0" arrival-time="0" start-time="0" exit-time="0" session="" thread="" ram_quota="0" ram_used="0"/>
		<task id="0" foc_id="0" execution-time="0" priority="0" core="0" policy-id="0" state="0" arrival-time="0" start-time="0" exit-time="0" session="" thread="" ram_quota="0" ram_used="0"/>
		<task id="0" foc_id="0" execution-time="0" priority="0" core="0" policy-id="0" state="0" arrival-time="0" start-time="0" exit-time="0" session="" thread="" ram_quota="0" ram_used="0"/>
		<task id="0" foc_id="0" execution-time="0" priority="0" core="0" policy-id="0" state="0" arrival-time="0" start-time="0" exit-time="0" session="" thread="" ram_quota="0" ram_used="0"/>
		<task id="0" foc_id="0" execution-time="0" priority="0" core="0" policy-id="0" state="0" arrival-time="0" start-time="0" exit-time="0" session="" thread="" ram_quota="0" ram_used="0"/>
		<task id="0" foc_id="0" execution-time="0" priority="0" core="0" policy-id="0" state="0" arrival-time="0" start-time="0" exit-time="0" session="" thread="" ram_quota="0" ram_used="0"/>
		<task id="0" foc_id="0" execution-time="0" priority="0" core="0" policy-id="0" state="0" arrival-time="0" start-time="0" exit-time="0" session="" thread="" ram_quota="0" ram_used="0"/>
		<task id="0" foc_id="0" execution-time="0" priority="0" core="0" policy-id="0" state="0" arrival-time="0" start-time="0" exit-time="0" session="" thread="" ram_quota="0" ram_used="0"/>
		<task id="0" foc_id="0" execution-time="0" priority="0" core="0" policy-id="0" state="0" arrival-time="0" start-time="0" exit-time="0" session="" thread="" ram_quota="0" ram_used="0"/>
		<task id="0" foc_id="0" execution-time="0" priority="0" core="0" policy-id="0" state="0" arrival-time="0" start-time="0" exit-time="0" session="" thread="" ram_quota="0" ram_used="0"/>
		<task id="0" foc_id="0" execution-time="0" priority="0" core="0" policy-id="0" state="0" arrival-time="0" start-time="0" exit-time="0" session="" thread="" ram_quota="0" ram_used="0"/>
		<task id="0" foc_id="0" execution-time="0" priority="0" core="0" policy-id="0" state="0" arrival-time="0" start-time="0" exit-time="0" session="" thread="" ram_quota="0" ram_used="0"/>
		<task id="0" foc_id="0" execution-time="0" priority="0" core="0" policy-id="0" state="0" arrival-time="0" start-time="0" exit-time="0" session="" thread="" ram_quota="0" ram_used="0"/>
		<task id="0" foc_id="0" execution-time="0" priority="0" core="0" policy-id="0" state="0" arrival-time="0" start-time="0" exit-time="0" session="" thread="" ram_quota="0" ram_used="0"/>
		<task id="0" foc_id="0" execution-time="0" priority="0" core="0" policy-id="0" state="0" arrival-time="0" start-time="0" exit-time="0" session="" thread="" ram_quota="0" ram_used="0"/>
		<task id="0" foc_id="0" execution-time="0" priority="0" core="0" policy-id="0" state="0" arrival-time="0" start-time="0" exit-time="0" session="" thread="" ram_quota="0" ram_used="0"/>
		<task id="0" foc_id="0" execution-time="0" priority="0" core="0" policy-id="0" state="0" arrival-time="0" start-time="0" exit-time="0" session="" thread="" ram_quota="0" ram_used="0"/>
		<task id="0" foc_id="0" execution-time="0" priority="0" core="0" policy-id="0" state="0" arrival-time="0" start-time="0" exit-time="0" session="" thread="" ram_quota="0" ram_used="0"/>
		<task id="0" foc_id="0" execution-time="0" priority="0" core="0" policy-id="0" state="0" arrival-time="0" start-time="0" exit-time="0" session="" thread="" ram_quota="0" ram_used="0"/>
		<task id="0" foc_id="0" execution-time="0" priority="0" core="0" policy-id="0" state="0" arrival-time="0" start-time="0" exit-time="0" session="" thread="" ram_quota="0" ram_used="0"/>
		<task id="0" foc_id="0" execution-time="0" priority="0" core="0" policy-id="0" state="0" arrival-time="0" start-time="0" exit-time="0" session="" thread="" ram_quota="0" ram_used="0"/>
		<task id="0" foc_id="0" execution-time="0" priority="0" core="0" policy-id="0" state="0" arrival-time="0" start-time="0" exit-time="0" session="" thread="" ram_quota="0" ram_used="0"/>
		<task id="0" foc_id="0" execution-time="0" priority="0" core="0" policy-id="0" state="0" arrival-time="0" start-time="0" exit-time="0" session="" thread="" ram_quota="0" ram_used="0"/>
		<task id="0" foc_id="0" execution-time="0" priority="0" core="0" policy-id="0" state="0" arrival-time="0" start-time="0" exit-time="0" session="" thread="" ram_quota="0" ram_used="0"/>
		<task id="0" foc_id="0" execution-time="0" priority="0" core="0" policy-id="0" state="0" arrival-time="0" start-time="0" exit-time="0" session="" thread="" ram_quota="0" ram_used="0"/>
		<task id="0" foc_id="0" execution-time="0" priority="0" core="0" policy-id="0" state="0" arrival-time="0" start-time="0" exit-time="0" session="" thread="" ram_quota="0" ram_used="0"/>
		<task id="0" foc_id="0" execution-time="0" priority="0" core="0" policy-id="0" state="0" arrival-time="0" start-time="0" exit-time="0" session="" thread="" ram_quota="0" ram_used="0"/>
		<task id="0" foc_id="0" execution-time="0" priority="0" core="0" policy-id="0" state="0" arrival-time="0" start-time="0" exit-time="0" session="" thread="" ram_quota="0" ram_used="0"/>
		<task id="0" foc_id="0" execution-time="0" priority="0" core="0" policy-id="0" state="0" arrival-time="0" start-time="0" exit-time="0" session="" thread="" ram_quota="0" ram_used="0"/>
		<task id="0" foc_id="0" execution-time="0" priority="0" core="0" policy-id="0" state="0" arrival-time="0" start-time="0" exit-time="0" session="" thread="" ram_quota="0" ram_used="0"/>
		<task id="0" foc_id="0" execution-time="0" priority="0" core="0" policy-id="0" state="0" arrival-time="0" start-time="0" exit-time="0" session="" thread="" ram_quota="0" ram_used="0"/>
		<task id="0" foc_id="0" execution-time="0" priority="0" core="0" policy-id="0" state="0" arrival-time="0" start-time="0" exit-time="0" session="" thread="" ram_quota="0" ram_used="0"/>
		<task id="0" foc_id="0" execution-time="0" priority="0" core="0" policy-id="0" state="0" arrival-time="0" start-time="0" exit-time="0" session="" thread="" ram_quota="0" ram_used="0"/>
		<task id="0" foc_id="0" execution-time="0" priority="0" core="0" policy-id="0" state="0" arrival-time="0" start-time="0" exit-time="0" session="" thread="" ram_quota="0" ram_used="0"/>
		<task id="0" foc_id="0" execution-time="0" priority="0" core="0" policy-id="0" state="0" arrival-time="0" start-time="0" exit-time="0" session="" thread="" ram_quota="0" ram_used="0"/>
		<task id="0" foc_id="0" execution-time="0" priority="0" core="0" policy-id="0" state="0" arrival-time="0" start-time="0" exit-time="0" session="" thread="" ram_quota="0" ram_used="0"/>
		<task id="0" foc_id="0" execution-time="0" priority="0" core="0" policy-id="0" state="0" arrival-time="0" start-time="0" exit-time="0" session="" thread="" ram_quota="0" ram_used="0"/>
	</task-descriptions>
</live>
<RIP_table RIP_table_size="26">
	<dead_task foc_id="38444" time="462156"/>
	<dead_task foc_id="38474" time="462384"/>
	<dead_task foc_id="38283" time="464372"/>
	<dead_task foc_id="38303" time="464433"/>
	<dead_task foc_id="38323" time="464496"/>
	<dead_task foc_id="38343" time="464556"/>
	<dead_task foc_id="38363" time="464616"/>
	<dead_task foc_id="38383" time="464676"/>
	<dead_task foc_id="38980" time="465786"/>
	<dead_task foc_id="39010" time="465844"/>
	<dead_task foc_id="38950" time="466158"/>
	<dead_task foc_id="38859" time="466485"/>
	<dead_task foc_id="38890" time="467569"/>
	<dead_task foc_id="38920" time="467688"/>
	<dead_task foc_id="38729" time="469707"/>
	<dead_task foc_id="38749" time="469768"/>
	<dead_task foc_id="38769" time="469828"/>
	<dead_task foc_id="38789" time="469888"/>
	<dead_task foc_id="38809" time="469948"/>
	<dead_task foc_id="38829" time="470008"/>
	<dead_task foc_id="39417" time="471008"/>
	<dead_task foc_id="39447" time="471199"/>
	<dead_task foc_id="39387" time="471476"/>
	<dead_task foc_id="39295" time="471835"/>
	<dead_task foc_id="39327" time="472875"/>
	<dead_task foc_id="39357" time="473107"/>
</RIP_table>